deadline_test_fixtures/__init__.py
deadline_test_fixtures/_version.py
deadline_test_fixtures/example_config.sh
deadline_test_fixtures/fixtures.py
deadline_test_fixtures/job_attachment_manager.py
deadline_test_fixtures/models.py
deadline_test_fixtures/py.typed
deadline_test_fixtures/pytest_hooks.py
deadline_test_fixtures/util.py
deadline_test_fixtures/cloudformation/__init__.py
deadline_test_fixtures/cloudformation/cfn.py
deadline_test_fixtures/cloudformation/util.py
deadline_test_fixtures/cloudformation/worker_bootstrap_stack.py
deadline_test_fixtures/containers/worker/Dockerfile
deadline_test_fixtures/containers/worker/run_container.sh
deadline_test_fixtures/deadline/__init__.py
deadline_test_fixtures/deadline/client.py
deadline_test_fixtures/deadline/resources.py
deadline_test_fixtures/deadline/stubs.py
deadline_test_fixtures/deadline/worker.py
deadline_cloud_test_fixtures-0.18.8.dist-info/METADATA
deadline_cloud_test_fixtures-0.18.8.dist-info/WHEEL
deadline_cloud_test_fixtures-0.18.8.dist-info/entry_points.txt
deadline_cloud_test_fixtures-0.18.8.dist-info/licenses/LICENSE
deadline_cloud_test_fixtures-0.18.8.dist-info/licenses/NOTICE
deadline_cloud_test_fixtures-0.18.8.dist-info/RECORD
