Metadata-Version: 2.4
Name: deadline-cloud-test-fixtures
Version: 0.18.8
Summary: This package contains pytest fixtures that are used to test AWS Deadline Cloud Python packages.
Project-URL: Homepage, https://github.com/aws-deadline/deadline-cloud-test-fixtures
Project-URL: Source, https://github.com/aws-deadline/deadline-cloud-test-fixtures
Author: Amazon Web Services
License-Expression: Apache-2.0
License-File: LICENSE
License-File: NOTICE
Classifier: Development Status :: 5 - Production/Stable
Classifier: Intended Audience :: Developers
Classifier: License :: OSI Approved :: Apache Software License
Classifier: Operating System :: MacOS
Classifier: Operating System :: Microsoft :: Windows
Classifier: Operating System :: POSIX :: Linux
Classifier: Programming Language :: Python
Classifier: Programming Language :: Python :: 3 :: Only
Classifier: Programming Language :: Python :: 3.9
Classifier: Programming Language :: Python :: 3.10
Classifier: Programming Language :: Python :: 3.11
Classifier: Programming Language :: Python :: 3.12
Requires-Python: >=3.9
Requires-Dist: boto3<2.0,>=1.34.75
Requires-Dist: botocore>=1.34.75
